guidellm/__init__.py
guidellm/config.py
guidellm/logger.py
guidellm/main.py
guidellm/backend/__init__.py
guidellm/backend/base.py
guidellm/backend/openai.py
guidellm/core/__init__.py
guidellm/core/distribution.py
guidellm/core/report.py
guidellm/core/request.py
guidellm/core/result.py
guidellm/core/serializable.py
guidellm/executor/__init__.py
guidellm/executor/base.py
guidellm/executor/profile_generator.py
guidellm/request/__init__.py
guidellm/request/base.py
guidellm/request/emulated.py
guidellm/request/file.py
guidellm/request/transformers.py
guidellm/scheduler/__init__.py
guidellm/scheduler/base.py
guidellm/scheduler/load_generator.py
guidellm/utils/__init__.py
guidellm/utils/injector.py
guidellm/utils/progress.py
guidellm/utils/text.py
guidellm/utils/transformers.py
guidellm_nightly-0.1.0.20240829.dist-info/LICENSE
guidellm_nightly-0.1.0.20240829.dist-info/METADATA
guidellm_nightly-0.1.0.20240829.dist-info/WHEEL
guidellm_nightly-0.1.0.20240829.dist-info/entry_points.txt
guidellm_nightly-0.1.0.20240829.dist-info/top_level.txt
guidellm_nightly-0.1.0.20240829.dist-info/RECORD
