Metadata-Version: 2.1
Name: guidellm-nightly
Version: 0.1.0.20240829
Summary: Guidance platform for deploying and managing large language models.
Author: Neuralmagic, Inc.
License: Apache License
Project-URL: homepage, https://github.com/neuralmagic/guidellm
Requires-Python: <4.0,>=3.8.0
License-File: LICENSE
Requires-Dist: click
Requires-Dist: datasets
Requires-Dist: ftfy>=6.0.0
Requires-Dist: loguru
Requires-Dist: numpy
Requires-Dist: openai
Requires-Dist: pydantic>=2.0.0
Requires-Dist: pydantic-settings>=2.0.0
Requires-Dist: pyyaml>=6.0.0
Requires-Dist: requests
Requires-Dist: rich
Requires-Dist: transformers
Provides-Extra: dev
Requires-Dist: pre-commit~=3.5.0; extra == "dev"
Requires-Dist: scipy~=1.10; extra == "dev"
Requires-Dist: sphinx~=7.1.2; extra == "dev"
Requires-Dist: tox~=4.16.0; extra == "dev"
Requires-Dist: pytest~=8.2.2; extra == "dev"
Requires-Dist: pytest-asyncio~=0.23.8; extra == "dev"
Requires-Dist: pytest-cov~=5.0.0; extra == "dev"
Requires-Dist: pytest-mock~=3.14.0; extra == "dev"
Requires-Dist: pytest-rerunfailures~=14.0; extra == "dev"
Requires-Dist: requests-mock~=1.12.1; extra == "dev"
Requires-Dist: mypy~=1.10.1; extra == "dev"
Requires-Dist: ruff~=0.5.2; extra == "dev"
Requires-Dist: mdformat~=0.7.17; extra == "dev"
Requires-Dist: mdformat-footnote~=0.1.1; extra == "dev"
Requires-Dist: mdformat-frontmatter~=2.0.8; extra == "dev"
Requires-Dist: mdformat-gfm~=0.3.6; extra == "dev"
Requires-Dist: types-click~=7.1.8; extra == "dev"
Requires-Dist: types-PyYAML~=6.0.1; extra == "dev"
Requires-Dist: types-requests~=2.32.0; extra == "dev"
Requires-Dist: types-toml; extra == "dev"
